onlinejudge_prepare/__init__.py
onlinejudge_prepare/main.py
onlinejudge_random/__init__.py
onlinejudge_template/__about__.py
onlinejudge_template/__init__.py
onlinejudge_template/main.py
onlinejudge_template/network.py
onlinejudge_template/types.py
onlinejudge_template/analyzer/__init__.py
onlinejudge_template/analyzer/codeforces.py
onlinejudge_template/analyzer/combined.py
onlinejudge_template/analyzer/constants.py
onlinejudge_template/analyzer/html.py
onlinejudge_template/analyzer/match.py
onlinejudge_template/analyzer/minimum_tree.py
onlinejudge_template/analyzer/node_util.py
onlinejudge_template/analyzer/output_types.py
onlinejudge_template/analyzer/parser.py
onlinejudge_template/analyzer/simple_patterns.py
onlinejudge_template/analyzer/simplify.py
onlinejudge_template/analyzer/topcoder.py
onlinejudge_template/analyzer/typing.py
onlinejudge_template/analyzer/variables.py
onlinejudge_template/generator/__init__.py
onlinejudge_template/generator/_cplusplus.py
onlinejudge_template/generator/_main.py
onlinejudge_template/generator/_python.py
onlinejudge_template/generator/_utils.py
onlinejudge_template/generator/about.py
onlinejudge_template/generator/cplusplus.py
onlinejudge_template/generator/hook.py
onlinejudge_template/generator/python.py
onlinejudge_template/generator/topcoder.py
onlinejudge_template_resources/__init__.py
onlinejudge_template_resources/template/customize_sample.cpp
onlinejudge_template_resources/template/fastio_sample.cpp
onlinejudge_template_resources/template/generate.cpp
onlinejudge_template_resources/template/generate.py
onlinejudge_template_resources/template/main.cpp
onlinejudge_template_resources/template/main.py
online_judge_template_generator-4.8.1.dist-info/LICENSE
online_judge_template_generator-4.8.1.dist-info/METADATA
online_judge_template_generator-4.8.1.dist-info/WHEEL
online_judge_template_generator-4.8.1.dist-info/entry_points.txt
online_judge_template_generator-4.8.1.dist-info/top_level.txt
online_judge_template_generator-4.8.1.dist-info/RECORD
