Metadata-Version: 2.1
Name: online-judge-template-generator
Version: 4.8.1
Summary: A simple template generator for competitive programming
Home-page: https://github.com/online-judge-tools/template-generator
Author: Kimiyuki Onaka
Author-email: kimiyuki95@gmail.com
License: MIT License
Platform: UNKNOWN
Classifier: Development Status :: 3 - Alpha
Classifier: Environment :: Console
Classifier: Intended Audience :: Developers
Classifier: License :: OSI Approved :: MIT License
Classifier: Operating System :: OS Independent
Classifier: Programming Language :: Python :: 3.6
Classifier: Topic :: Internet :: WWW/HTTP
Classifier: Topic :: Software Development :: Code Generators
Classifier: Topic :: Utilities
Requires-Python: >=3.6
Requires-Dist: appdirs (>=1.4)
Requires-Dist: beautifulsoup4 (>=4.8)
Requires-Dist: colorlog (>=4.2.1)
Requires-Dist: Mako (>=1.1)
Requires-Dist: online-judge-api-client (>=10.8.0)
Requires-Dist: online-judge-tools (>=10)
Requires-Dist: ply (>=3)
Requires-Dist: pyyaml (>=5)
Requires-Dist: requests (>=2.23)
Requires-Dist: toml (>=0.10)
Provides-Extra: dev
Requires-Dist: isort (==5.5.2) ; extra == 'dev'
Requires-Dist: mypy (==0.782) ; extra == 'dev'
Requires-Dist: pylint (==2.6.0) ; extra == 'dev'
Requires-Dist: yapf (==0.30.0) ; extra == 'dev'
Provides-Extra: doc
Requires-Dist: sphinx (>=2.4) ; extra == 'doc'
Requires-Dist: sphinx-rtd-theme (>=0.4) ; extra == 'doc'
